cookieplone/__init__.py
cookieplone/__main__.py
cookieplone/_types.py
cookieplone/cli.py
cookieplone/data.py
cookieplone/exceptions.py
cookieplone/generator.py
cookieplone/logger.py
cookieplone/repository.py
cookieplone/settings.py
cookieplone/filters/__init__.py
cookieplone/templates/__init__.py
cookieplone/templates/fixtures.py
cookieplone/templates/types.py
cookieplone/utils/__init__.py
cookieplone/utils/console.py
cookieplone/utils/containers.py
cookieplone/utils/files.py
cookieplone/utils/formatters.py
cookieplone/utils/git.py
cookieplone/utils/internal.py
cookieplone/utils/npm.py
cookieplone/utils/plone.py
cookieplone/utils/sanity.py
cookieplone/utils/validators.py
cookieplone/utils/versions.py
cookieplone/utils/commands/__init__.py
cookieplone-0.9.10.dist-info/METADATA
cookieplone-0.9.10.dist-info/WHEEL
cookieplone-0.9.10.dist-info/entry_points.txt
cookieplone-0.9.10.dist-info/licenses/LICENSE
cookieplone-0.9.10.dist-info/RECORD
