Metadata-Version: 2.4
Name: cookieplone
Version: 0.9.10
Summary: Create Plone projects, add-ons, documentation with ease!
Project-URL: Documentation, https://github.com/plone/cookieplone#readme
Project-URL: Issues, https://github.com/plone/cookieplone/issues
Project-URL: Source, https://github.com/plone/cookieplone
Author-email: Plone Community <dev@plone.org>
License-Expression: MIT
License-File: LICENSE
Keywords: Plone,code generator,cookiecutter
Classifier: Development Status :: 5 - Production/Stable
Classifier: Environment :: Console
Classifier: Intended Audience :: Developers
Classifier: License :: OSI Approved :: MIT License
Classifier: Natural Language :: English
Classifier: Programming Language :: Python
Classifier: Programming Language :: Python :: 3
Classifier: Programming Language :: Python :: 3 :: Only
Classifier: Programming Language :: Python :: 3.10
Classifier: Programming Language :: Python :: 3.11
Classifier: Programming Language :: Python :: 3.12
Classifier: Programming Language :: Python :: 3.13
Classifier: Programming Language :: Python :: Implementation :: CPython
Classifier: Topic :: Software Development
Classifier: Topic :: Software Development :: Code Generators
Requires-Python: >=3.10
Requires-Dist: black==24.4.2
Requires-Dist: cookiecutter==2.6.0
Requires-Dist: gitpython==3.1.43
Requires-Dist: isort
Requires-Dist: packaging==24.0
Requires-Dist: ruff
Requires-Dist: semver==3.0.2
Requires-Dist: typer==0.17.4
Requires-Dist: xmltodict==0.13.0
Requires-Dist: zpretty
